CHANGES.txt
MANIFEST.in
README.txt
setup.py
collective/__init__.py
collective.teamwork.egg-info/PKG-INFO
collective.teamwork.egg-info/SOURCES.txt
collective.teamwork.egg-info/dependency_links.txt
collective.teamwork.egg-info/entry_points.txt
collective.teamwork.egg-info/namespace_packages.txt
collective.teamwork.egg-info/not-zip-safe
collective.teamwork.egg-info/requires.txt
collective.teamwork.egg-info/top_level.txt
collective/teamwork/TODO.txt
collective/teamwork/__init__.py
collective/teamwork/configure.zcml
collective/teamwork/interfaces.py
collective/teamwork/overrides.zcml
collective/teamwork/patch.py
collective/teamwork/profiles.zcml
collective/teamwork/setuphandlers.py
collective/teamwork/zope2.py
collective/teamwork/browser/__init__.py
collective/teamwork/browser/configure.zcml
collective/teamwork/browser/helper.py
collective/teamwork/browser/membercsv.py
collective/teamwork/browser/membership.pt
collective/teamwork/browser/membership.py
collective/teamwork/browser/purgeuser.pt
collective/teamwork/browser/purgeuser.py
collective/teamwork/browser/rosterview.pt
collective/teamwork/browser/rosterview.py
collective/teamwork/browser/unavailable.pt
collective/teamwork/browser/userdata.py
collective/teamwork/browser/userinfo.pt
collective/teamwork/browser/userinfo.py
collective/teamwork/browser/userprops.pt
collective/teamwork/browser/resources/go-top.png
collective/teamwork/browser/resources/homefolder.png
collective/teamwork/browser/resources/membership.css
collective/teamwork/browser/resources/membership.js
collective/teamwork/browser/resources/teamwork.css
collective/teamwork/browser/resources/workspace.png
collective/teamwork/content/__init__.py
collective/teamwork/content/configure.zcml
collective/teamwork/content/interfaces.py
collective/teamwork/content/permissions.zcml
collective/teamwork/profiles/default/actions.xml
collective/teamwork/profiles/default/browserlayer.xml
collective/teamwork/profiles/default/catalog.xml
collective/teamwork/profiles/default/cssregistry.xml
collective/teamwork/profiles/default/import_steps.xml
collective/teamwork/profiles/default/memberdata_properties.xml
collective/teamwork/profiles/default/metadata.xml
collective/teamwork/profiles/default/propertiestool.xml
collective/teamwork/profiles/default/rolemap.xml
collective/teamwork/profiles/default/skins.xml
