Metadata-Version: 1.0
Name: collective.teamwork
Version: 0.9
Summary: Plone add-on for workspace/workgroup components.
Home-page: http://github.com/collective
Author: Sean Upton
Author-email: sean.upton@hsc.utah.edu
License: GPL
Platform: UNKNOWN
Classifier: Programming Language :: Python
Classifier: Framework :: Plone
